MCMarkerMaker/__init__.py
mcmarkermaker-0.1.0.dist-info/METADATA
mcmarkermaker-0.1.0.dist-info/WHEEL
mcmarkermaker-0.1.0.dist-info/licenses/LICENSE
mcmarkermaker-0.1.0.dist-info/RECORD
