Metadata-Version: 2.4
Name: MCMarkerMaker
Version: 0.1.0
Summary: A simple utility to create Avid Media Composer marker import files.
Project-URL: Homepage, https://github.com/lawson-tanner/MCMarkerMaker
Project-URL: Bug Tracker, https://github.com/lawson-tanner/MCMarkerMaker/issues
Author-email: Lawson Tanner <lawson.tanner@gmail.com>
License-File: LICENSE
Classifier: License :: OSI Approved :: MIT License
Classifier: Operating System :: OS Independent
Classifier: Programming Language :: Python :: 3
Classifier: Topic :: Multimedia :: Video
Requires-Python: >=3.8
